sheet2vcf
