Metadata-Version: 2.4
Name: sheet2vcf
Version: 1.0
Summary: Simple and efficient tool to export contact numbers from CSV sheets to VCF format
Home-page: https://github.com/MohamedElsayed-debug/sheet2vcf
Author: Mohamed Elsayed
Author-email: ms.moh.dev@gmail.com
Project-URL: Source, https://github.com/MohamedElsayed-debug/sheet2vcf
Classifier: Programming Language :: Python :: 3
Classifier: Operating System :: OS Independent
Classifier: License :: OSI Approved :: MIT License
License-File: LICENSE.txt
Dynamic: author
Dynamic: author-email
Dynamic: classifier
Dynamic: description
Dynamic: description-content-type
Dynamic: home-page
Dynamic: license-file
Dynamic: project-url
Dynamic: summary
